README.md
setup.py
azpytools/__init__.py
azpytools/ai.py
azpytools/utils.py
azpytools.egg-info/PKG-INFO
azpytools.egg-info/SOURCES.txt
azpytools.egg-info/dependency_links.txt
azpytools.egg-info/top_level.txt
azpytools/common/__init__.py
azpytools/common/config.py
azpytools/common/excel.py
azpytools/common/ocr.py
azpytools/common/pdf.py
azpytools/common/pinyin.py
azpytools/common/spider.py
azpytools/common/stock.py
azpytools/common/word.py
azpytools/database/__init__.py
azpytools/database/mongodb.py
azpytools/database/mysql.py