Metadata-Version: 2.1
Name: azpytools
Version: 1.1.12
Summary: Tools for Python development
Author: AndyZhu
Author-email: andyzhu@live.com
